kaggle/LICENSE
kaggle/__init__.py
kaggle/cli.py
kaggle/configuration.py
kaggle/api/__init__.py
kaggle/api/kaggle_api.py
kaggle/api/kaggle_api_extended.py
kaggle/models/__init__.py
kaggle/models/api_blob_type.py
kaggle/models/dataset_column.py
kaggle/models/dataset_new_request.py
kaggle/models/dataset_new_version_request.py
kaggle/models/dataset_update_settings_request.py
kaggle/models/kaggle_models_extended.py
kaggle/models/kernel_push_request.py
kaggle/models/model_instance_new_version_request.py
kaggle/models/model_instance_update_request.py
kaggle/models/model_new_instance_request.py
kaggle/models/model_new_request.py
kaggle/models/model_update_request.py
kaggle/models/start_blob_upload_request.py
kaggle/models/start_blob_upload_response.py
kaggle/models/upload_file.py
kaggle/test/__init__.py
kaggle/test/test_authenticate.py
kagglesdk/LICENSE
kagglesdk/__init__.py
kagglesdk/kaggle_client.py
kagglesdk/kaggle_env.py
kagglesdk/kaggle_http_client.py
kagglesdk/kaggle_object.py
kagglesdk/admin/__init__.py
kagglesdk/admin/services/__init__.py
kagglesdk/admin/services/inbox_file_service.py
kagglesdk/admin/types/__init__.py
kagglesdk/admin/types/inbox_file_service.py
kagglesdk/blobs/__init__.py
kagglesdk/blobs/services/__init__.py
kagglesdk/blobs/services/blob_api_service.py
kagglesdk/blobs/types/__init__.py
kagglesdk/blobs/types/blob_api_service.py
kagglesdk/common/__init__.py
kagglesdk/common/types/__init__.py
kagglesdk/common/types/file_download.py
kagglesdk/common/types/http_redirect.py
kagglesdk/competitions/__init__.py
kagglesdk/competitions/services/__init__.py
kagglesdk/competitions/services/competition_api_service.py
kagglesdk/competitions/types/__init__.py
kagglesdk/competitions/types/competition_api_service.py
kagglesdk/competitions/types/competition_enums.py
kagglesdk/competitions/types/submission_status.py
kagglesdk/datasets/__init__.py
kagglesdk/datasets/services/__init__.py
kagglesdk/datasets/services/dataset_api_service.py
kaggle-1.7.4.1.dist-info/METADATA
kaggle-1.7.4.1.dist-info/WHEEL
kaggle-1.7.4.1.dist-info/entry_points.txt
kaggle-1.7.4.1.dist-info/licenses/LICENSE.txt
kaggle-1.7.4.1.dist-info/RECORD
